llamarker/.streamlit/config.toml
llamarker/__init__.py
llamarker/assets/Llamarker_logo.png
llamarker/assets/llamarker_demo.gif
llamarker/file_to_pdf_converter.py
llamarker/gui_runner.py
llamarker/img_processor.py
llamarker/llamarker_gui.py
llamarker/main.py
llamarker-1.0.2.dist-info/LICENSE
llamarker-1.0.2.dist-info/METADATA
llamarker-1.0.2.dist-info/WHEEL
llamarker-1.0.2.dist-info/entry_points.txt
llamarker-1.0.2.dist-info/RECORD
