Metadata-Version: 2.3
Name: llamarker
Version: 1.0.2
Summary: A universal GenAI-based local parser for complex documents of all types.
License: GPL-3.0-or-later
Keywords: markdown,document parsing,llama,AI,local parser,genai
Author: Revan Kumar Dhanasekaran
Author-email: revan.dhana@gmail.com
Requires-Python: >=3.10,<4.0
Classifier: License :: OSI Approved :: GNU General Public License v3 or later (GPLv3+)
Classifier: Programming Language :: Python :: 3
Classifier: Programming Language :: Python :: 3.10
Classifier: Programming Language :: Python :: 3.11
Classifier: Programming Language :: Python :: 3.12
Classifier: Programming Language :: Python :: 3.13
Requires-Dist: matplotlib (<3.10.0)
Requires-Dist: ollama (>=0.4.4,<0.5.0)
Requires-Dist: pydantic (>=2.10.4,<3.0.0)
Requires-Dist: pypdf (>=5.1.0,<6.0.0)
Requires-Dist: pypdf2 (>=3.0.1,<4.0.0)
Requires-Dist: streamlit (>=1.41.1,<2.0.0)
Project-URL: Homepage, https://github.com/RevanKumarD/LlaMarker
Project-URL: Repository, https://github.com/RevanKumarD/LlaMarker
